rt_pytest_sanic/__init__.py
rt_pytest_sanic/plugin.py
rt_pytest_sanic/utils.py
rt_pytest_sanic-2.0.0.dist-info/LICENSE
rt_pytest_sanic-2.0.0.dist-info/METADATA
rt_pytest_sanic-2.0.0.dist-info/WHEEL
rt_pytest_sanic-2.0.0.dist-info/entry_points.txt
rt_pytest_sanic-2.0.0.dist-info/RECORD
