Metadata-Version: 2.1
Name: rt-pytest-sanic
Version: 2.0.0
Summary: a pytest plugin for Sanic
Home-page: https://github.com/x-amer-ngmx/rt-pytest-sanic
License: MIT
Author: naguwal
Author-email: naguwal@gmail.com
Requires-Python: >=3.7
Classifier: License :: OSI Approved :: MIT License
Classifier: Programming Language :: Python :: 3
Classifier: Programming Language :: Python :: 3.7
Classifier: Programming Language :: Python :: 3.8
Classifier: Programming Language :: Python :: 3.9
Classifier: Programming Language :: Python :: 3.10
Classifier: Programming Language :: Python :: 3.11
Classifier: Programming Language :: Python :: 3.12
Classifier: Topic :: Software Development :: Libraries :: Python Modules
Requires-Dist: async_generator (>=1.10,<2.0)
Requires-Dist: httpx (>=0.18.1)
Requires-Dist: pytest (>=5.2)
Requires-Dist: websockets (>=9.1,<11.0)
Project-URL: Documentation, https://pytest-sanic.readthedocs.io/en/latest/
Project-URL: Repository, https://github.com/x-amer-ngmx/rt-pytest-sanic
